rouigram/__init__.py
rouigram/package_data.dat
rouigram-2.1.3.data/data/my_data/data_file
rouigram-2.1.3.dist-info/LICENSE.txt
rouigram-2.1.3.dist-info/METADATA
rouigram-2.1.3.dist-info/WHEEL
rouigram-2.1.3.dist-info/entry_points.txt
rouigram-2.1.3.dist-info/top_level.txt
rouigram-2.1.3.dist-info/RECORD
