Metadata-Version: 2.1
Name: rouigram
Version: 2.1.3
Summary: first instagram Api for user id without any registration
Home-page: https://github.com/MohammadaliMirhamed/rouigram.py/
Author: Mohammadali Mirhamed Roui
Author-email: mamalirooy@gmail.com
License: UNKNOWN
Project-URL: Bug Reports, https://github.com/MohammadaliMirhamed/rouigram.py/issues
Project-URL: Funding, https://donate.pypi.org
Project-URL: Say Thanks!, https://saythanks.io/to/MohammadaliMirhamed
Project-URL: Source, https://github.com/MohammadaliMirhamed/rouigram.py/
Keywords: instagram api hack rouigram mirhamed roui
Platform: UNKNOWN
Classifier: Development Status :: 3 - Alpha
Classifier: Intended Audience :: Developers
Classifier: Topic :: Software Development :: Build Tools
Classifier: License :: OSI Approved :: MIT License
Classifier: Programming Language :: Python :: 2
Classifier: Programming Language :: Python :: 2.7
Classifier: Programming Language :: Python :: 3
Classifier: Programming Language :: Python :: 3.4
Classifier: Programming Language :: Python :: 3.5
Classifier: Programming Language :: Python :: 3.6
Classifier: Programming Language :: Python :: 3.7
Requires-Dist: requests
Requires-Dist: urlopen
Provides-Extra: dev
Requires-Dist: check-manifest; extra == 'dev'
Provides-Extra: test
Requires-Dist: coverage; extra == 'test'
